es_sql-2.0.0.dist-info/metadata.json
es_sql-2.0.0.dist-info/top_level.txt
es_sql-2.0.0.dist-info/RECORD
es_sql-2.0.0.dist-info/DESCRIPTION.rst
es_sql-2.0.0.dist-info/WHEEL
es_sql-2.0.0.dist-info/METADATA
es_sql-2.0.0.dist-info/entry_points.txt
es_sql/__main__.py
es_sql/__init__.py
es_sql/es_query.py
es_sql/sqlparse/filters.py
es_sql/sqlparse/sql_select_test.py
es_sql/sqlparse/keywords.py
es_sql/sqlparse/lexer.py
es_sql/sqlparse/datetime_evaluator_test.py
es_sql/sqlparse/ordereddict.py
es_sql/sqlparse/datetime_evaluator.py
es_sql/sqlparse/functions.py
es_sql/sqlparse/exceptions.py
es_sql/sqlparse/compat.py
es_sql/sqlparse/pipeline.py
es_sql/sqlparse/utils.py
es_sql/sqlparse/formatter.py
es_sql/sqlparse/sql.py
es_sql/sqlparse/__init__.py
es_sql/sqlparse/sql_select.py
es_sql/sqlparse/tokens.py
es_sql/sqlparse/engine/filter.py
es_sql/sqlparse/engine/grouping.py
es_sql/sqlparse/engine/__init__.py
es_sql/executors/select_inside_executor.py
es_sql/executors/select_from_system.py
es_sql/executors/__init__.py
es_sql/executors/select_from_leaf_executor.py
es_sql/executors/translators/bucket_script_translator.py
es_sql/executors/translators/sort_translator.py
es_sql/executors/translators/join_translator.py
es_sql/executors/translators/group_by_translator.py
es_sql/executors/translators/case_when_translator.py
es_sql/executors/translators/doc_script_translator.py
es_sql/executors/translators/filter_translator.py
es_sql/executors/translators/__init__.py
es_sql/executors/translators/metric_translator.py
es_sql/tests/execute_sql_test.py
es_sql/tests/__init__.py
es_sql/tests/join/server_side_join_test.py
es_sql/tests/join/client_size_join_test.py
es_sql/tests/join/__init__.py
es_sql/tests/select_from_leaf/order_by_test.py
es_sql/tests/select_from_leaf/projections_test.py
es_sql/tests/select_from_leaf/where_test.py
es_sql/tests/select_from_leaf/__init__.py
es_sql/tests/select_inside_leaf/order_by_test.py
es_sql/tests/select_inside_leaf/group_by_test.py
es_sql/tests/select_inside_leaf/metric_test.py
es_sql/tests/select_inside_leaf/response_test.py
es_sql/tests/select_inside_leaf/having_test.py
es_sql/tests/select_inside_leaf/__init__.py
