Metadata-Version: 2.0
Name: es-sql
Version: 2.0.0
Summary: Use sql to query from Elasticsearch
Home-page: https://github.com/taowen/es-monitor
Author: Tao Wen
Author-email: taowen@gmail.com
License: Apache License, Version 2.0
Keywords: sql elasticsearch es
Platform: UNKNOWN
Classifier: Development Status :: 4 - Beta
Classifier: License :: OSI Approved :: Apache Software License
Classifier: Intended Audience :: Developers
Classifier: Operating System :: OS Independent
Classifier: Programming Language :: Python
Classifier: Programming Language :: Python :: 2
Classifier: Programming Language :: Python :: 2.6
Classifier: Programming Language :: Python :: 2.7
Classifier: Programming Language :: Python :: Implementation :: CPython
Classifier: Programming Language :: Python :: Implementation :: PyPy
